.coveragerc
.hgignore
.hgtags
.travis.yml
CHANGES.txt
HACKING.txt
LICENSE.txt
README.md
README.txt
pytest.ini
setup.py
tox.ini
src/pyramid_scales/__init__.py
src/pyramid_scales/tests.py
src/pyramid_scales.egg-info/PKG-INFO
src/pyramid_scales.egg-info/SOURCES.txt
src/pyramid_scales.egg-info/dependency_links.txt
src/pyramid_scales.egg-info/not-zip-safe
src/pyramid_scales.egg-info/requires.txt
src/pyramid_scales.egg-info/top_level.txt