Metadata-Version: 1.0
Name: pyramid-scales
Version: 1.1
Summary: Viewing scales metrics from Pyramid
Home-page: https://bitbucket.org/wosc/pyramid_scales
Author: Wolfgang Schnerring <ws@gocept.com>
Author-email: ws@gocept.com
License: BSD
Platform: UNKNOWN
